flowcept/__init__.py
flowcept/cli.py
flowcept/configs.py
flowcept/version.py
flowcept/agents/__init__.py
flowcept/agents/agent_client.py
flowcept/agents/agents_utils.py
flowcept/agents/dynamic_schema_tracker.py
flowcept/agents/flowcept_agent.py
flowcept/agents/flowcept_ctx_manager.py
flowcept/agents/gui/__init__.py
flowcept/agents/gui/agent_gui.py
flowcept/agents/gui/audio_utils.py
flowcept/agents/gui/gui_utils.py
flowcept/agents/llms/__init__.py
flowcept/agents/llms/claude_gcp.py
flowcept/agents/llms/gemini25.py
flowcept/agents/prompts/__init__.py
flowcept/agents/prompts/general_prompts.py
flowcept/agents/prompts/in_memory_query_prompts.py
flowcept/agents/tools/__init__.py
flowcept/agents/tools/general_tools.py
flowcept/agents/tools/in_memory_queries/__init__.py
flowcept/agents/tools/in_memory_queries/in_memory_queries_tools.py
flowcept/agents/tools/in_memory_queries/pandas_agent_utils.py
flowcept/analytics/__init__.py
flowcept/analytics/analytics_utils.py
flowcept/analytics/data_augmentation.py
flowcept/analytics/plot.py
flowcept/commons/__init__.py
flowcept/commons/autoflush_buffer.py
flowcept/commons/flowcept_logger.py
flowcept/commons/query_utils.py
flowcept/commons/settings_factory.py
flowcept/commons/task_data_preprocess.py
flowcept/commons/utils.py
flowcept/commons/vocabulary.py
flowcept/commons/daos/__init__.py
flowcept/commons/daos/keyvalue_dao.py
flowcept/commons/daos/redis_conn.py
flowcept/commons/daos/docdb_dao/__init__.py
flowcept/commons/daos/docdb_dao/docdb_dao_base.py
flowcept/commons/daos/docdb_dao/lmdb_dao.py
flowcept/commons/daos/docdb_dao/mongodb_dao.py
flowcept/commons/daos/mq_dao/__init__.py
flowcept/commons/daos/mq_dao/mq_dao_base.py
flowcept/commons/daos/mq_dao/mq_dao_kafka.py
flowcept/commons/daos/mq_dao/mq_dao_mofka.py
flowcept/commons/daos/mq_dao/mq_dao_redis.py
flowcept/commons/flowcept_dataclasses/__init__.py
flowcept/commons/flowcept_dataclasses/base_settings_dataclasses.py
flowcept/commons/flowcept_dataclasses/task_object.py
flowcept-0.9.17.dist-info/METADATA
flowcept-0.9.17.dist-info/WHEEL
flowcept-0.9.17.dist-info/entry_points.txt
flowcept-0.9.17.dist-info/licenses/LICENSE
flowcept-0.9.17.dist-info/RECORD
