Metadata-Version: 2.4
Name: flowcept
Version: 0.9.17
Summary: Capture and query workflow provenance data using data observability
Author: Oak Ridge National Laboratory
License-Expression: MIT
License-File: LICENSE
Keywords: agentic-ai,agentic-workflows,ai,big-data,dask,data-analytics,data-integration,databases,lineage,llm,machine-learning,ml,mlflow,model-management,parallel-processing,provenance,reproducibility,responsible-ai,scientific-workflows,tensorboard,workflows
Classifier: License :: OSI Approved :: MIT License
Classifier: Operating System :: OS Independent
Classifier: Programming Language :: Python :: 3
Requires-Python: >=3.11
Requires-Dist: msgpack
Requires-Dist: numpy
Requires-Dist: omegaconf
Requires-Dist: orjson
Provides-Extra: all
Requires-Dist: alembic; extra == 'all'
Requires-Dist: confluent-kafka<=2.8.0; extra == 'all'
Requires-Dist: cryptography; extra == 'all'
Requires-Dist: dask[distributed]<=2024.10.0; extra == 'all'
Requires-Dist: flask-restful; extra == 'all'
Requires-Dist: furo; extra == 'all'
Requires-Dist: gitpython; extra == 'all'
Requires-Dist: google-genai; extra == 'all'
Requires-Dist: jupyterlab; extra == 'all'
Requires-Dist: langchain-community; extra == 'all'
Requires-Dist: langchain-openai; extra == 'all'
Requires-Dist: lmdb; extra == 'all'
Requires-Dist: matplotlib; extra == 'all'
Requires-Dist: mcp[cli]; extra == 'all'
Requires-Dist: mlflow-skinny; extra == 'all'
Requires-Dist: nbmake; extra == 'all'
Requires-Dist: paho-mqtt; extra == 'all'
Requires-Dist: pandas; extra == 'all'
Requires-Dist: pika; extra == 'all'
Requires-Dist: plotly; extra == 'all'
Requires-Dist: psutil>=6.1.1; extra == 'all'
Requires-Dist: py-cpuinfo; extra == 'all'
Requires-Dist: pyarrow; extra == 'all'
Requires-Dist: pymongo; extra == 'all'
Requires-Dist: pymupdf; extra == 'all'
Requires-Dist: pytest; extra == 'all'
Requires-Dist: pyyaml; extra == 'all'
Requires-Dist: redis; extra == 'all'
Requires-Dist: requests; extra == 'all'
Requires-Dist: ruff; extra == 'all'
Requires-Dist: scipy; extra == 'all'
Requires-Dist: seaborn; extra == 'all'
Requires-Dist: sphinx; extra == 'all'
Requires-Dist: sqlalchemy; extra == 'all'
Requires-Dist: streamlit; extra == 'all'
Requires-Dist: tbparse; extra == 'all'
Requires-Dist: tensorboard; extra == 'all'
Requires-Dist: tensorflow; extra == 'all'
Requires-Dist: tomli; extra == 'all'
Requires-Dist: watchdog; extra == 'all'
Provides-Extra: analytics
Requires-Dist: matplotlib; extra == 'analytics'
Requires-Dist: plotly; extra == 'analytics'
Requires-Dist: scipy; extra == 'analytics'
Requires-Dist: seaborn; extra == 'analytics'
Provides-Extra: dask
Requires-Dist: dask[distributed]<=2024.10.0; extra == 'dask'
Requires-Dist: tomli; extra == 'dask'
Provides-Extra: dev
Requires-Dist: furo; extra == 'dev'
Requires-Dist: jupyterlab; extra == 'dev'
Requires-Dist: nbmake; extra == 'dev'
Requires-Dist: pika; extra == 'dev'
Requires-Dist: pytest; extra == 'dev'
Requires-Dist: pyyaml; extra == 'dev'
Requires-Dist: ruff; extra == 'dev'
Requires-Dist: sphinx; extra == 'dev'
Provides-Extra: docs
Requires-Dist: furo; extra == 'docs'
Requires-Dist: sphinx; extra == 'docs'
Provides-Extra: extras
Requires-Dist: flask-restful; extra == 'extras'
Requires-Dist: gitpython; extra == 'extras'
Requires-Dist: pandas; extra == 'extras'
Requires-Dist: psutil>=6.1.1; extra == 'extras'
Requires-Dist: py-cpuinfo; extra == 'extras'
Requires-Dist: pyarrow; extra == 'extras'
Requires-Dist: pymongo; extra == 'extras'
Requires-Dist: redis; extra == 'extras'
Requires-Dist: requests; extra == 'extras'
Provides-Extra: kafka
Requires-Dist: confluent-kafka<=2.8.0; extra == 'kafka'
Provides-Extra: llm-agent
Requires-Dist: langchain-community; extra == 'llm-agent'
Requires-Dist: langchain-openai; extra == 'llm-agent'
Requires-Dist: matplotlib; extra == 'llm-agent'
Requires-Dist: mcp[cli]; extra == 'llm-agent'
Requires-Dist: pymupdf; extra == 'llm-agent'
Requires-Dist: streamlit; extra == 'llm-agent'
Provides-Extra: llm-agent-audio
Requires-Dist: gtts; extra == 'llm-agent-audio'
Requires-Dist: langchain-community; extra == 'llm-agent-audio'
Requires-Dist: langchain-openai; extra == 'llm-agent-audio'
Requires-Dist: matplotlib; extra == 'llm-agent-audio'
Requires-Dist: mcp[cli]; extra == 'llm-agent-audio'
Requires-Dist: pydub; extra == 'llm-agent-audio'
Requires-Dist: pymupdf; extra == 'llm-agent-audio'
Requires-Dist: speechrecognition; extra == 'llm-agent-audio'
Requires-Dist: streamlit; extra == 'llm-agent-audio'
Requires-Dist: streamlit-mic-recorder; extra == 'llm-agent-audio'
Provides-Extra: llm-google
Requires-Dist: google-genai; extra == 'llm-google'
Requires-Dist: langchain-community; extra == 'llm-google'
Requires-Dist: langchain-openai; extra == 'llm-google'
Requires-Dist: matplotlib; extra == 'llm-google'
Requires-Dist: mcp[cli]; extra == 'llm-google'
Requires-Dist: pymupdf; extra == 'llm-google'
Requires-Dist: streamlit; extra == 'llm-google'
Provides-Extra: lmdb
Requires-Dist: lmdb; extra == 'lmdb'
Provides-Extra: ml-dev
Requires-Dist: datasets==2.17.0; extra == 'ml-dev'
Requires-Dist: nltk; extra == 'ml-dev'
Requires-Dist: numpy<2.0; extra == 'ml-dev'
Requires-Dist: sacremoses; extra == 'ml-dev'
Requires-Dist: torch==2.2.2; extra == 'ml-dev'
Requires-Dist: torchtext==0.17.2; extra == 'ml-dev'
Requires-Dist: torchvision==0.17.2; extra == 'ml-dev'
Provides-Extra: mlflow
Requires-Dist: alembic; extra == 'mlflow'
Requires-Dist: cryptography; extra == 'mlflow'
Requires-Dist: mlflow-skinny; extra == 'mlflow'
Requires-Dist: sqlalchemy; extra == 'mlflow'
Requires-Dist: watchdog; extra == 'mlflow'
Provides-Extra: mongo
Requires-Dist: pyarrow; extra == 'mongo'
Requires-Dist: pymongo; extra == 'mongo'
Provides-Extra: mqtt
Requires-Dist: paho-mqtt; extra == 'mqtt'
Provides-Extra: nvidia
Requires-Dist: nvidia-ml-py; extra == 'nvidia'
Provides-Extra: redis
Requires-Dist: redis; extra == 'redis'
Provides-Extra: telemetry
Requires-Dist: psutil>=6.1.1; extra == 'telemetry'
Requires-Dist: py-cpuinfo; extra == 'telemetry'
Provides-Extra: tensorboard
Requires-Dist: tbparse; extra == 'tensorboard'
Requires-Dist: tensorboard; extra == 'tensorboard'
Requires-Dist: tensorflow; extra == 'tensorboard'
